asynckivy_ext/queue.py
asynckivy_ext_queue-0.2.0.dist-info/LICENSE
asynckivy_ext_queue-0.2.0.dist-info/METADATA
asynckivy_ext_queue-0.2.0.dist-info/WHEEL
asynckivy_ext_queue-0.2.0.dist-info/RECORD
