Metadata-Version: 2.1
Name: asynckivy-ext-queue
Version: 0.2.0
Summary: Extension for asynckivy programs
Home-page: https://github.com/asyncgui/asynckivy-ext-queue
License: MIT
Author: Nattōsai Mitō
Author-email: flow4re2c@gmail.com
Requires-Python: >=3.9,<4.0
Classifier: Development Status :: 3 - Alpha
Classifier: Intended Audience :: Developers
Classifier: License :: OSI Approved :: MIT License
Classifier: Operating System :: OS Independent
Classifier: Programming Language :: Python
Classifier: Programming Language :: Python :: 3
Classifier: Programming Language :: Python :: 3.9
Classifier: Programming Language :: Python :: 3.10
Classifier: Programming Language :: Python :: 3.11
Classifier: Topic :: Software Development :: Libraries
Requires-Dist: asynckivy (>=0.6,<0.7)
Project-URL: Repository, https://github.com/asyncgui/asynckivy-ext-queue
